<?xml version="1.0" encoding="utf-8"?><StartElement><element><PkgType>Spell</PkgType><PkgName>tt1</PkgName><ActivationKey>f</ActivationKey><ExpGiven>10</ExpGiven></element><element><PkgType>Spell</PkgType><PkgName>tt2</PkgName><ActivationKey>g</ActivationKey><ExpGiven>10</ExpGiven></element><element><PkgType>Spell</PkgType><PkgName>tt3</PkgName><ActivationKey>h</ActivationKey><ExpGiven>10</ExpGiven></element><element><PkgType>Spell</PkgType><PkgName>tt4</PkgName><ActivationKey>j</ActivationKey><ExpGiven>10</ExpGiven></element><element><PkgType>Stat</PkgType><PkgName>Wis</PkgName><ActivationKey></ActivationKey><ExpGiven>10</ExpGiven></element><element><PkgType>Stat</PkgType><PkgName>Int</PkgName><ActivationKey></ActivationKey><ExpGiven>10</ExpGiven></element><element><LoopAmt>2</LoopAmt></element><EndElement /></StartElement>